{
  "frames": {
    "allyRCounter.png": {
      "frame": {
        "x": 0,
        "y": 0,
        "w": 18,
        "h": 27
      },
      "rotated": false,
      "trimmed": true,
      "spriteSourceSize": {
        "x": 7,
        "y": 3,
        "w": 18,
        "h": 27
      },
      "sourceSize": {
        "w": 32,
        "h": 32
      },
      "pivot": {
        "x": 0.5,
        "y": 0.5
      }
    }
  },
  "animations": {
    "contador": [
      "allyRCounter.png"
    ]
  },
  "meta": {
    "app": "http://free-tex-packer.com",
    "version": "0.6.7",
    "image": "allyRCounter.png",
    "format": "RGBA8888",
    "size": {
      "w": 18,
      "h": 27
    },
    "scale": 1
  }
}